repassh/__init__.py
repassh/knock.py
repassh/ssh.py
repassh-1.2.0.dist-info/entry_points.txt
repassh-1.2.0.dist-info/LICENSE.ssh-ident
repassh-1.2.0.dist-info/LICENSE
repassh-1.2.0.dist-info/WHEEL
repassh-1.2.0.dist-info/METADATA
repassh-1.2.0.dist-info/RECORD
