Metadata-Version: 2.1
Name: repassh
Version: 1.2.0
Summary: SSH wrapper to load private keys on first execution
Home-page: https://github.com/dyuri/repassh
License: MIT
Author: Gyuri Horak
Author-email: dyuri@horak.hu
Requires-Python: >=3.6,<4.0
Classifier: Environment :: Console
Classifier: Intended Audience :: End Users/Desktop
Classifier: License :: OSI Approved :: MIT License
Classifier: Operating System :: OS Independent
Classifier: Programming Language :: Python
Classifier: Programming Language :: Python :: 3
Classifier: Programming Language :: Python :: 3.10
Classifier: Programming Language :: Python :: 3.6
Classifier: Programming Language :: Python :: 3.7
Classifier: Programming Language :: Python :: 3.8
Classifier: Programming Language :: Python :: 3.9
Project-URL: Repository, https://github.com/dyuri/repassh
